LogCenterInterceptor/InterceptorMiddleware.py
LogCenterInterceptor/InterceptorOptions.py
LogCenterInterceptor/LoggerFactory.py
LogCenterInterceptor/__init__.py
logcenter_requestlogger-0.1.2.dist-info/METADATA
logcenter_requestlogger-0.1.2.dist-info/WHEEL
logcenter_requestlogger-0.1.2.dist-info/top_level.txt
logcenter_requestlogger-0.1.2.dist-info/RECORD
