Metadata-Version: 2.4
Name: LogCenter.RequestLogger
Version: 0.1.2
Summary: This lib will send your app's request and responses from FastAPI to LogCenter automatically.
Author-email: Hudson Ventura <hudsonventura@outlook.com>
Project-URL: Homepage, https://github.com/hudsonventura/LogCenter
Project-URL: Bug Tracker, https://github.com/hudsonventura/LogCenter/issues
Requires-Python: >=3.7
Requires-Dist: python-dateutil
Requires-Dist: uuid
Requires-Dist: requests
